README.rst
setup.py
slacker/__init__.py
slacker/bio.py
slacker/geventbackend.py
slacker/protocol.py
slacker/proxy.py
slacker_python.egg-info/PKG-INFO
slacker_python.egg-info/SOURCES.txt
slacker_python.egg-info/dependency_links.txt
slacker_python.egg-info/requires.txt
slacker_python.egg-info/top_level.txt