Metadata-Version: 1.1
Name: slacker-python
Version: 0.3.0
Summary: python client of slacker RPC
Home-page: http://github.com/sunng87/slacker-python
Author: Sun Ning
Author-email: sunng@about.me
License: mit
Platform: UNKNOWN
Classifier: Development Status :: 3 - Alpha
Classifier: Intended Audience :: Developers
Classifier: License :: OSI Approved :: MIT License
Classifier: Topic :: Software Development
Classifier: Programming Language :: Python
Classifier: Operating System :: OS Independent
